{"edges":[{"fromNode":0,"toNode":2,"weight":2},{"fromNode":0,"toNode":1,"weight":4},{"fromNode":1,"toNode":3,"weight":3},{"fromNode":2,"toNode":3,"weight":8},{"fromNode":2,"toNode":1,"weight":1},{"fromNode":3,"toNode":4,"weight":1}],"nodes":[{"nodeID":0,"nodeLabel":"A","nodeValue":0},{"nodeID":1,"nodeLabel":"B","nodeValue":0},{"nodeID":2,"nodeLabel":"C","nodeValue":0},{"nodeID":3,"nodeLabel":"D","nodeValue":0},{"nodeID":4,"nodeLabel":"E","nodeValue":0}],"steps":[{"distances":null,"highlightedEdges":[],"highlightedNodes":["A"]},{"distances":null,"highlightedEdges":[["A","C"]],"highlightedNodes":["A","C"]},{"distances":null,"highlightedEdges":[],"highlightedNodes":["C"]},{"distances":null,"highlightedEdges":[["C","D"]],"highlightedNodes":["C","D"]},{"distances":null,"highlightedEdges":[],"highlightedNodes":["D"]},{"distances":null,"highlightedEdges":[["D","E"]],"highlightedNodes":["D","E"]},{"distances":null,"highlightedEdges":[],"highlightedNodes":["E"]},{"distances":null,"highlightedEdges":[["C","B"]],"highlightedNodes":["C","B"]},{"distances":null,"highlightedEdges":[],"highlightedNodes":["B"]}]}